dxxtools/__init__.py
dxxtools/upsampling.py
dxxtools/vs_plot.py
dxxtools-0.1.4.dist-info/LICENSE.txt
dxxtools-0.1.4.dist-info/METADATA
dxxtools-0.1.4.dist-info/WHEEL
dxxtools-0.1.4.dist-info/entry_points.txt
dxxtools-0.1.4.dist-info/top_level.txt
dxxtools-0.1.4.dist-info/RECORD
