Metadata-Version: 2.1
Name: dxxtools
Version: 0.1.4
Summary: dxxtools is a package of useful tools for .DXX
Home-page: https://github.com/tetsuzawa/spatial-research/tree/master/modules/dxxtools
Author: Tetsu Takizawa
Author-email: tetsu.varmos@gmail.com
License: UNKNOWN
Platform: UNKNOWN
Requires-Dist: dxx
Requires-Dist: numpy
Requires-Dist: matplotlib
